Lab3/src/bram11.v
// bram behavior code (can't be synthesis)
// 11 words
module bram11 
(
    CLK,
    WE,
    EN,
    Di,
    Do,
    A
);

    input   wire            CLK;
    input   wire    [3:0]   WE;
    input   wire            EN;
    input   wire    [31:0]  Di;
    output  wire     [31:0]  Do;
    input   wire    [11:0]   A; 

    //  11 words
	reg [31:0] RAM[0:10];
    reg [11:0] r_A;

    always @(posedge CLK) begin
        r_A <= A;
    end

    assign Do = {32{EN}} & RAM[r_A>>2];    // read

    reg [31:0] Temp_D;
    always @(posedge CLK) begin
        if(EN) begin
	    if(WE[0]) RAM[A>>2][7:0] <= Di[7:0];
            if(WE[1]) RAM[A>>2][15:8] <= Di[15:8];
            if(WE[2]) RAM[A>>2][23:16] <= Di[23:16];
            if(WE[3]) RAM[A>>2][31:24] <= Di[31:24];
        end
    end

endmodule

Lab3/src/fir.v
`include "bram11.v"
module fir 
#(  
    parameter pADDR_WIDTH = 12,
    parameter pDATA_WIDTH = 32,
    parameter Tape_Num    = 11
)
(
    // AXI4-Lite Write Address Channel
    output wire                     awready,
    output wire                     wready,
    input  wire                     awvalid,
    input  wire [pADDR_WIDTH-1:0]   awaddr,
    input  wire                     wvalid,
    input  wire [pDATA_WIDTH-1:0]   wdata,
    
    // AXI4-Lite Read Address Channel
    output wire                     arready,
    input  wire                     rready,
    input  wire                     arvalid,
    input  wire [pADDR_WIDTH-1:0]   araddr,
    output wire                     rvalid,
    output wire [pDATA_WIDTH-1:0]   rdata,    
    
    // AXI-Stream Input
    input  wire                     ss_tvalid, 
    input  wire [pDATA_WIDTH-1:0]   ss_tdata, 
    input  wire                     ss_tlast, 
    output wire                     ss_tready, 
    
    // AXI-Stream Output
    input  wire                     sm_tready, 
    output wire                     sm_tvalid, 
    output wire [pDATA_WIDTH-1:0]   sm_tdata, 
    output wire                     sm_tlast, 
    
    // Tap BRAM Interface
    output wire [3:0]               tap_WE,
    output wire                     tap_EN,
    output wire [pDATA_WIDTH-1:0]   tap_Di,
    output wire [pADDR_WIDTH-1:0]   tap_A,
    inout  wire [pDATA_WIDTH-1:0]   tap_Do,

    // Data BRAM Interface
    output wire [3:0]               data_WE,
    output wire                     data_EN,
    output wire [pDATA_WIDTH-1:0]   data_Di,
    output wire [pADDR_WIDTH-1:0]   data_A,
    inout  wire [pDATA_WIDTH-1:0]   data_Do,

    input  wire                     axis_clk,
    input  wire                     axis_rst_n
);

    // AXI4-Lite Control Logic
    reg axi_awready;
    reg axi_wready;
    reg axi_arready;
    reg [pDATA_WIDTH-1:0] axi_rdata_reg;
    reg axi_rvalid;

    // Internal Registers
    reg [pADDR_WIDTH-1:0] write_ptr = 0;
    reg [pADDR_WIDTH-1:0] read_ptr = 0;
    reg [pDATA_WIDTH-1:0] acc = 0;
    reg [4:0] tap_cnt = 0;
    reg calc_done = 0;
    reg [2:0] state = 0;

    // AXI-Stream Control
    assign ss_tready = (write_ptr < (2**pADDR_WIDTH - 1));
    assign sm_tvalid = calc_done;
    assign sm_tlast = calc_done;
    assign sm_tdata = acc;

    // AXI4-Lite Write Channel
    assign awready = axi_awready;
    assign wready = axi_wready;

    always @(posedge axis_clk) begin
        if (!axis_rst_n) begin
            axi_awready <= 0;
            axi_wready <= 0;
        end else begin
            axi_awready <= awvalid && !axi_awready;
            axi_wready <= wvalid && !axi_wready;
        end
    end

    // AXI4-Lite Read Channel
    assign arready = axi_arready;
    assign rvalid = axi_rvalid;
    assign rdata = axi_rdata_reg;

    always @(posedge axis_clk) begin
        if (!axis_rst_n) begin
            axi_arready <= 0;
            axi_rvalid <= 0;
        end else if (arvalid && !axi_arready) begin
            axi_arready <= 1;
            axi_rvalid <= 1;
            if (araddr < Tape_Num)
                axi_rdata_reg <= tap_Do;  // Read from coefficient BRAM
            else
                axi_rdata_reg <= 0;
        end else begin
            axi_arready <= 0;
            if (rready) axi_rvalid <= 0;
        end
    end

    // Data BRAM Write Control
    assign data_WE = (ss_tvalid && ss_tready) ? 4'b1111 : 4'b0000;
    assign data_EN = 1'b1;
    assign data_Di = ss_tdata;
    assign data_A = (state == 1 && tap_cnt < Tape_Num) ? (read_ptr - tap_cnt) : 0;

    // Tap BRAM Write Control
    assign tap_WE = (awvalid && awready) ? 4'b1111 : 4'b0000;
    assign tap_EN = 1'b1;
    assign tap_Di = wdata;
    assign tap_A = (state == 1 && tap_cnt < Tape_Num) ? tap_cnt : 0;

    // Data Write Process
    always @(posedge axis_clk) begin
        if (!axis_rst_n) begin
            write_ptr <= 0;
        end else if (ss_tvalid && ss_tready) begin
            write_ptr <= write_ptr + 1;
        end
    end

    // FIR Calculation FSM
    always @(posedge axis_clk) begin
        if (!axis_rst_n) begin
            state <= 0;
            acc <= 0;
            tap_cnt <= 0;
            calc_done <= 0;
        end else begin
            case(state)
                0: begin  // Idle
                    if (sm_tready) begin
                        read_ptr <= write_ptr - Tape_Num;
                        state <= 1;
                    end
                end
                1: begin  // Multiply-Accumulate
                    if (tap_cnt < Tape_Num) begin
                        acc <= acc + (data_Do * tap_Do);
                        tap_cnt <= tap_cnt + 1;
                    end else begin
                        calc_done <= 1;
                        state <= 2;
                    end
                end
                2: begin  // Wait for output ready
                    if (sm_tready) begin
                        calc_done <= 0;
                        acc <= 0;
                        tap_cnt <= 0;
                        state <= 0;
                    end
                end
            endcase
        end
    end

    // Instantiation of BRAM modules
    bram11 tap_bram (
        .CLK(axis_clk),
        .WE(tap_WE),
        .EN(tap_EN),
        .Di(tap_Di),
        .Do(tap_Do),
        .A(tap_A)
    );

    bram11 data_bram (
        .CLK(axis_clk),
        .WE(data_WE),
        .EN(data_EN),
        .Di(data_Di),
        .Do(data_Do),
        .A(data_A)
    );

endmodule

Lab3/src/fir_tb.v
`timescale 1ns / 1ps
`include "fir.v"
//////////////////////////////////////////////////////////////////////////////////
// Company: 
// Engineer: 
// 
// Create Date: 08/20/2023 10:38:55 AM
// Design Name: 
// Module Name: fir_tb
// Project Name: 
// Target Devices: 
// Tool Versions: 
// Description: 
// 
// Dependencies: 
// 
// Revision:
// Revision 0.01 - File Created
// Additional Comments:
// 
//////////////////////////////////////////////////////////////////////////////////


module fir_tb
#(  parameter pADDR_WIDTH = 12,
    parameter pDATA_WIDTH = 32,
    parameter Tape_Num    = 11,
    parameter Data_Num    = 600
)(
    input  [(pDATA_WIDTH-1):0] tap_Do,
    input  [(pDATA_WIDTH-1):0] data_Do
);
    wire                        awready;
    wire                        wready;
    reg                         awvalid;
    reg   [(pADDR_WIDTH-1): 0]  awaddr;
    reg                         wvalid;
    reg signed [(pDATA_WIDTH-1) : 0] wdata;
    wire                        arready;
    reg                         rready;
    reg                         arvalid;
    reg         [(pADDR_WIDTH-1): 0] araddr;
    wire                        rvalid;
    wire signed [(pDATA_WIDTH-1): 0] rdata;
    reg                         ss_tvalid;
    reg signed [(pDATA_WIDTH-1) : 0] ss_tdata;
    reg                         ss_tlast;
    wire                        ss_tready;
    reg                         sm_tready;
    wire                        sm_tvalid;
    wire signed [(pDATA_WIDTH-1) : 0] sm_tdata;
    wire                        sm_tlast;
    reg                         axis_clk;
    reg                         axis_rst_n;

// ram for tap
    wire [3:0]               tap_WE;
    wire                     tap_EN;
    wire [(pDATA_WIDTH-1):0] tap_Di;
    wire [(pADDR_WIDTH-1):0] tap_A;
    

// ram for data RAM
    wire [3:0]               data_WE;
    wire                     data_EN;
    wire [(pDATA_WIDTH-1):0] data_Di;
    wire [(pADDR_WIDTH-1):0] data_A;



    fir fir_DUT(
        .awready(awready),
        .wready(wready),
        .awvalid(awvalid),
        .awaddr(awaddr),
        .wvalid(wvalid),
        .wdata(wdata),
        .arready(arready),
        .rready(rready),
        .arvalid(arvalid),
        .araddr(araddr),
        .rvalid(rvalid),
        .rdata(rdata),
        .ss_tvalid(ss_tvalid),
        .ss_tdata(ss_tdata),
        .ss_tlast(ss_tlast),
        .ss_tready(ss_tready),
        .sm_tready(sm_tready),
        .sm_tvalid(sm_tvalid),
        .sm_tdata(sm_tdata),
        .sm_tlast(sm_tlast),

        // ram for tap
        .tap_WE(tap_WE),
        .tap_EN(tap_EN),
        .tap_Di(tap_Di),
        .tap_A(tap_A),
        .tap_Do(tap_Do),

        // ram for data
        .data_WE(data_WE),
        .data_EN(data_EN),
        .data_Di(data_Di),
        .data_A(data_A),
        .data_Do(data_Do),

        .axis_clk(axis_clk),
        .axis_rst_n(axis_rst_n)

        );
    
    // RAM for tap
    bram11 tap_RAM (
        .CLK(axis_clk),
        .WE(tap_WE),
        .EN(tap_EN),
        .Di(tap_Di),
        .A(tap_A),
        .Do(tap_Do)
    );

    // RAM for data: choose bram11 or bram12
    bram11 data_RAM(
        .CLK(axis_clk),
        .WE(data_WE),
        .EN(data_EN),
        .Di(data_Di),
        .A(data_A),
        .Do(data_Do)
    );

    reg signed [(pDATA_WIDTH-1):0] Din_list[0:(Data_Num-1)];
    reg signed [(pDATA_WIDTH-1):0] golden_list[0:(Data_Num-1)];

    initial begin
        $dumpfile("fir.vcd");
        $dumpvars();
    end


    initial begin
        axis_clk = 0;
        forever begin
            #5 axis_clk = (~axis_clk);
        end
    end

    initial begin
        axis_rst_n = 0;
        @(posedge axis_clk); @(posedge axis_clk);
        axis_rst_n = 1;
    end

    reg [31:0]  data_length;
    integer Din, golden, input_data, golden_data, m;
    initial begin
        data_length = 0;
        Din = $fopen("./samples_triangular_wave.dat","r");
        golden = $fopen("./out_gold.dat","r");
        for(m=0;m<Data_Num;m=m+1) begin
            input_data = $fscanf(Din,"%d", Din_list[m]);
            golden_data = $fscanf(golden,"%d", golden_list[m]);
            data_length = data_length + 1;
        end
    end

    integer i;
    initial begin
        $display("------------Start simulation-----------");
        ss_tvalid = 0;
        $display("----Start the data input(AXI-Stream)----");
        for(i=0;i<(data_length-1);i=i+1) begin
            ss_tlast = 0; ss(Din_list[i]);
        end
        config_read_check(12'h00, 32'h00, 32'h0000_000f); // check idle = 0
        ss_tlast = 1; ss(Din_list[(Data_Num-1)]);
        $display("------End the data input(AXI-Stream)------");
    end

    integer k;
    reg error;
    reg status_error;
    initial begin
        error = 0; status_error = 0;
        sm_tready = 1;
        wait (sm_tvalid);
        for(k=0;k < data_length;k=k+1) begin
            sm(golden_list[k],k);
        end
        config_read_check(12'h00, 32'h02, 32'h0000_0002); // check ap_done = 1 (0x00 [bit 1])
        config_read_check(12'h00, 32'h04, 32'h0000_0004); // check ap_idle = 1 (0x00 [bit 2])
        if (error == 0 & error_coef == 0) begin
            $display("---------------------------------------------");
            $display("-----------Congratulations! Pass-------------");
        end
        else begin
            $display("--------Simulation Failed---------");
        end
        $finish;
    end

    // Prevent hang
    integer timeout = (1000000);
    initial begin
        while(timeout > 0) begin
            @(posedge axis_clk);
            timeout = timeout - 1;
        end
        $display($time, "Simualtion Hang ....");
        $finish;
    end


    reg signed [31:0] coef[0:10]; // fill in coef 
    initial begin
        coef[0]  =  32'd0;
        coef[1]  = -32'd10;
        coef[2]  = -32'd9;
        coef[3]  =  32'd23;
        coef[4]  =  32'd56;
        coef[5]  =  32'd63;
        coef[6]  =  32'd56;
        coef[7]  =  32'd23;
        coef[8]  = -32'd9;
        coef[9]  = -32'd10;
        coef[10] =  32'd0;
    end

    reg error_coef;
    initial begin
        error_coef = 0;
        $display("----Start the coefficient input(AXI-lite)----");
        config_write(12'h10, data_length);
        for(k=0; k< Tape_Num; k=k+1) begin
            config_write(12'h20+4*k, coef[k]);
        end
        awvalid <= 0; wvalid <= 0;
        // read-back and check
        $display(" Check Coefficient ...");
        for(k=0; k < Tape_Num; k=k+1) begin
            config_read_check(12'h20+4*k, coef[k], 32'hffffffff);
        end
        arvalid <= 0;
        $display(" Tape programming done ...");
        $display(" Start FIR");
        @(posedge axis_clk) config_write(12'h00, 32'h0000_0001);    // ap_start = 1
        $display("----End the coefficient input(AXI-lite)----");
    end

    task config_write;
        input [11:0]    addr;
        input [31:0]    data;
        begin
            awvalid <= 0; wvalid <= 0;
            @(posedge axis_clk);
            awvalid <= 1; awaddr <= addr;
            wvalid  <= 1; wdata <= data;
            @(posedge axis_clk);
            while (!wready) @(posedge axis_clk);
        end
    endtask

    task config_read_check;
        input [11:0]        addr;
        input signed [31:0] exp_data;
        input [31:0]        mask;
        begin
            arvalid <= 0;
            @(posedge axis_clk);
            arvalid <= 1; araddr <= addr;
            rready <= 1;
            @(posedge axis_clk);
            while (!rvalid) @(posedge axis_clk);
            if( (rdata & mask) != (exp_data & mask)) begin
                $display("ERROR: exp = %d, rdata = %d", exp_data, rdata);
                error_coef <= 1;
            end else begin
                $display("OK: exp = %d, rdata = %d", exp_data, rdata);
            end
        end
    endtask



    task ss;
        input  signed [31:0] in1;
        begin
            ss_tvalid <= 1;
            ss_tdata  <= in1;
            @(posedge axis_clk);
            while (!ss_tready) begin
                @(posedge axis_clk);
            end
        end
    endtask

    task sm;
        input  signed [31:0] in2; // golden data
        input         [31:0] pcnt; // pattern count
        begin
            sm_tready <= 1;
            @(posedge axis_clk) 
            wait(sm_tvalid);
            while(!sm_tvalid) @(posedge axis_clk);
            if (sm_tdata != in2) begin
                $display("[ERROR] [Pattern %d] Golden answer: %d, Your answer: %d", pcnt, in2, sm_tdata);
                error <= 1;
            end
            else begin
                $display("[PASS] [Pattern %d] Golden answer: %d, Your answer: %d", pcnt, in2, sm_tdata);
            end
            @(posedge axis_clk);
        end
    endtask
endmodule

Lab3/src/fir.vcd
$date
	Sun Mar 16 20:13:36 2025
$end
$version
	Icarus Verilog
$end
$timescale
	1ps
$end
$scope module fir_tb $end
$var wire 32 ! data_Do [31:0] $end
$var wire 1 " data_EN $end
$var wire 32 # tap_Do [31:0] $end
$var wire 1 $ tap_EN $end
$var wire 1 % wready $end
$var wire 4 & tap_WE [3:0] $end
$var wire 32 ' tap_Di [31:0] $end
$var wire 12 ( tap_A [11:0] $end
$var wire 1 ) ss_tready $end
$var wire 1 * sm_tvalid $end
$var wire 1 + sm_tlast $end
$var wire 32 , sm_tdata [31:0] $end
$var wire 1 - rvalid $end
$var wire 32 . rdata [31:0] $end
$var wire 4 / data_WE [3:0] $end
$var wire 32 0 data_Di [31:0] $end
$var wire 12 1 data_A [11:0] $end
$var wire 1 2 awready $end
$var wire 1 3 arready $end
$var parameter 32 4 Data_Num $end
$var parameter 32 5 Tape_Num $end
$var parameter 32 6 pADDR_WIDTH $end
$var parameter 32 7 pDATA_WIDTH $end
$var reg 12 8 araddr [11:0] $end
$var reg 1 9 arvalid $end
$var reg 12 : awaddr [11:0] $end
$var reg 1 ; awvalid $end
$var reg 1 < axis_clk $end
$var reg 1 = axis_rst_n $end
$var reg 32 > data_length [31:0] $end
$var reg 1 ? error $end
$var reg 1 @ error_coef $end
$var reg 1 A rready $end
$var reg 1 B sm_tready $end
$var reg 32 C ss_tdata [31:0] $end
$var reg 1 D ss_tlast $end
$var reg 1 E ss_tvalid $end
$var reg 1 F status_error $end
$var reg 32 G wdata [31:0] $end
$var reg 1 H wvalid $end
$var integer 32 I Din [31:0] $end
$var integer 32 J golden [31:0] $end
$var integer 32 K golden_data [31:0] $end
$var integer 32 L i [31:0] $end
$var integer 32 M input_data [31:0] $end
$var integer 32 N k [31:0] $end
$var integer 32 O m [31:0] $end
$var integer 32 P timeout [31:0] $end
$scope module data_RAM $end
$var wire 1 < CLK $end
$var wire 32 Q Do [31:0] $end
$var wire 1 " EN $end
$var wire 4 R WE [3:0] $end
$var wire 32 S Di [31:0] $end
$var wire 12 T A [11:0] $end
$var reg 12 U r_A [11:0] $end
$upscope $end
$scope module fir_DUT $end
$var wire 12 V araddr [11:0] $end
$var wire 1 3 arready $end
$var wire 1 9 arvalid $end
$var wire 12 W awaddr [11:0] $end
$var wire 1 ; awvalid $end
$var wire 1 < axis_clk $end
$var wire 1 = axis_rst_n $end
$var wire 32 X data_Di [31:0] $end
$var wire 32 Y data_Do [31:0] $end
$var wire 1 " data_EN $end
$var wire 32 Z rdata [31:0] $end
$var wire 1 A rready $end
$var wire 1 - rvalid $end
$var wire 32 [ sm_tdata [31:0] $end
$var wire 1 + sm_tlast $end
$var wire 1 B sm_tready $end
$var wire 1 * sm_tvalid $end
$var wire 32 \ ss_tdata [31:0] $end
$var wire 1 D ss_tlast $end
$var wire 1 E ss_tvalid $end
$var wire 32 ] tap_Di [31:0] $end
$var wire 32 ^ tap_Do [31:0] $end
$var wire 1 $ tap_EN $end
$var wire 32 _ wdata [31:0] $end
$var wire 1 % wready $end
$var wire 1 H wvalid $end
$var wire 4 ` tap_WE [3:0] $end
$var wire 12 a tap_A [11:0] $end
$var wire 1 ) ss_tready $end
$var wire 4 b data_WE [3:0] $end
$var wire 12 c data_A [11:0] $end
$var wire 1 2 awready $end
$var parameter 32 d Tape_Num $end
$var parameter 32 e pADDR_WIDTH $end
$var parameter 32 f pDATA_WIDTH $end
$var reg 32 g acc [31:0] $end
$var reg 1 h axi_arready $end
$var reg 1 2 axi_awready $end
$var reg 32 i axi_rdata_reg [31:0] $end
$var reg 1 j axi_rvalid $end
$var reg 1 k axi_wready $end
$var reg 1 l calc_done $end
$var reg 12 m read_ptr [11:0] $end
$var reg 3 n state [2:0] $end
$var reg 5 o tap_cnt [4:0] $end
$var reg 12 p write_ptr [11:0] $end
$scope module data_bram $end
$var wire 12 q A [11:0] $end
$var wire 1 < CLK $end
$var wire 32 r Di [31:0] $end
$var wire 32 s Do [31:0] $end
$var wire 1 " EN $end
$var wire 4 t WE [3:0] $end
$var reg 12 u r_A [11:0] $end
$upscope $end
$scope module tap_bram $end
$var wire 12 v A [11:0] $end
$var wire 1 < CLK $end
$var wire 32 w Di [31:0] $end
$var wire 32 x Do [31:0] $end
$var wire 1 $ EN $end
$var wire 4 y WE [3:0] $end
$var reg 12 z r_A [11:0] $end
$upscope $end
$upscope $end
$scope module tap_RAM $end
$var wire 12 { A [11:0] $end
$var wire 1 < CLK $end
$var wire 32 | Di [31:0] $end
$var wire 32 } Do [31:0] $end
$var wire 1 $ EN $end
$var wire 4 ~ WE [3:0] $end
$var reg 12 !" r_A [11:0] $end
$upscope $end
$scope task config_read_check $end
$var reg 12 "" addr [11:0] $end
$var reg 32 #" exp_data [31:0] $end
$var reg 32 $" mask [31:0] $end
$upscope $end
$scope task config_write $end
$var reg 12 %" addr [11:0] $end
$var reg 32 &" data [31:0] $end
$upscope $end
$scope task sm $end
$var reg 32 '" in2 [31:0] $end
$var reg 32 (" pcnt [31:0] $end
$upscope $end
$scope task ss $end
$var reg 32 )" in1 [31:0] $end
$upscope $end
$upscope $end
$enddefinitions $end
$comment Show the parameter values. $end
$dumpall
b100000 f
b1100 e
b1011 d
b100000 7
b1100 6
b1011 5
b1001011000 4
$end
#0
$dumpvars
b1 )"
bx ("
bx '"
b1001011000 &"
b10000 %"
bx $"
bx #"
bx ""
bx !"
b0 ~
bx }
bx |
b0 {
bx z
b0 y
bx x
bx w
b0 v
bx u
b1111 t
bx s
b1 r
b0 q
b0 p
b0 o
b0 n
b0 m
0l
xk
xj
bx i
xh
b0 g
b0 c
b1111 b
b0 a
b0 `
bx _
bx ^
bx ]
b1 \
b0 [
bx Z
bx Y
b1 X
bx W
bx V
bx U
b0 T
b1 S
b1111 R
bx Q
b11110100001001000000 P
b1001011000 O
bx N
b1 M
b0 L
b1 K
b10000000000000000000000000000100 J
b10000000000000000000000000000011 I
0H
bx G
0F
1E
0D
b1 C
1B
xA
0@
0?
b1001011000 >
0=
0<
0;
bx :
x9
bx 8
x3
x2
b0 1
b1 0
b1111 /
bx .
x-
b0 ,
0+
0*
1)
b0 (
bx '
b0 &
x%
1$
bx #
1"
bx !
$end
#5000
b1 !
b1 Q
b1 Y
b1 s
b10 0
b10 S
b10 X
b10 r
b10 C
b10 \
b0 z
b0 u
0%
0k
02
0-
0j
03
0h
b0 !"
b0 U
b1001011000 '
b1001011000 ]
b1001011000 w
b1001011000 |
b1001011000 G
b1001011000 _
1H
b10000 :
b10000 W
1;
b10 )"
b1 L
b11110100001000111111 P
1<
#10000
0<
#15000
b10 !
b10 Q
b10 Y
b10 s
b11 0
b11 S
b11 X
b11 r
b11 C
b11 \
b11 )"
b10 L
b11110100001000111110 P
1=
1<
#20000
0<
#25000
b1111 &
b1111 `
b1111 y
b1111 ~
b111111110101 1
b111111110101 T
b111111110101 c
b111111110101 q
b11 !
b11 Q
b11 Y
b11 s
b100 0
b100 S
b100 X
b100 r
b100 C
b100 \
1%
1k
12
b1 p
b1 n
b111111110101 m
b100 )"
b11 L
b11110100001000111101 P
1<
#30000
0<
#35000
b0 &
b0 `
b0 y
b0 ~
bx !
bx Q
bx Y
bx s
b1001011000 #
b1001011000 ^
b1001011000 x
b1001011000 }
b111111110100 1
b111111110100 T
b111111110100 c
b111111110100 q
b1 (
b1 a
b1 v
b1 {
b101 0
b101 S
b101 X
b101 r
b101 C
b101 \
0H
0;
b111111110101 U
b1 o
bx ,
bx [
bx g
b10 p
0%
0k
02
b111111110101 u
b101 )"
b100 L
b0 &"
b100000 %"
b0 N
b11110100001000111100 P
1<
#40000
0<
#45000
b111111110011 1
b111111110011 T
b111111110011 c
b111111110011 q
b10 (
b10 a
b10 v
b10 {
b110 0
b110 S
b110 X
b110 r
b110 C
b110 \
b1 z
b111111110100 u
b11 p
b10 o
b1 !"
b111111110100 U
b0 '
b0 ]
b0 w
b0 |
b0 G
b0 _
1H
b100000 :
b100000 W
1;
b110 )"
b101 L
b11110100001000111011 P
1<
#50000
0<
#55000
b1111 &
b1111 `
b1111 y
b1111 ~
b111111110010 1
b111111110010 T
b111111110010 c
b111111110010 q
b11 (
b11 a
b11 v
b11 {
b111 0
b111 S
b111 X
b111 r
b111 C
b111 \
b111111110011 U
b10 !"
b11 o
b100 p
1%
1k
12
b111111110011 u
b10 z
b111 )"
b110 L
b11110100001000111010 P
1<
#60000
0<
#65000
b0 &
b0 `
b0 y
b0 ~
b111111110001 1
b111111110001 T
b111111110001 c
b111111110001 q
b100 (
b100 a
b100 v
b100 {
b0 #
b0 ^
b0 x
b0 }
b1000 0
b1000 S
b1000 X
b1000 r
b1000 C
b1000 \
0H
0;
b11 z
b111111110010 u
0%
0k
02
b101 p
b100 o
b11 !"
b111111110010 U
b1000 )"
b111 L
b11111111111111111111111111110110 &"
b100100 %"
b1 N
b11110100001000111001 P
1<
#70000
0<
#75000
bx #
bx ^
bx x
bx }
b111111110000 1
b111111110000 T
b111111110000 c
b111111110000 q
b101 (
b101 a
b101 v
b101 {
b1001 0
b1001 S
b1001 X
b1001 r
b1001 C
b1001 \
b111111110001 U
b100 !"
b101 o
b110 p
b111111110001 u
b100 z
b11111111111111111111111111110110 '
b11111111111111111111111111110110 ]
b11111111111111111111111111110110 w
b11111111111111111111111111110110 |
b11111111111111111111111111110110 G
b11111111111111111111111111110110 _
1H
b100100 :
b100100 W
1;
b1001 )"
b1000 L
b11110100001000111000 P
1<
#80000
0<
#85000
b1111 &
b1111 `
b1111 y
b1111 ~
b111111101111 1
b111111101111 T
b111111101111 c
b111111101111 q
b110 (
b110 a
b110 v
b110 {
b1010 0
b1010 S
b1010 X
b1010 r
b1010 C
b1010 \
b101 z
b111111110000 u
1%
1k
12
b111 p
b110 o
b101 !"
b111111110000 U
b1010 )"
b1001 L
b11110100001000110111 P
1<
#90000
0<
#95000
b0 &
b0 `
b0 y
b0 ~
b11111111111111111111111111110110 #
b11111111111111111111111111110110 ^
b11111111111111111111111111110110 x
b11111111111111111111111111110110 }
b111111101110 1
b111111101110 T
b111111101110 c
b111111101110 q
b111 (
b111 a
b111 v
b111 {
b1011 0
b1011 S
b1011 X
b1011 r
b1011 C
b1011 \
0H
0;
b111111101111 U
b110 !"
b111 o
b1000 p
0%
0k
02
b111111101111 u
b110 z
b1011 )"
b1010 L
b11111111111111111111111111110111 &"
b101000 %"
b10 N
b11110100001000110110 P
1<
#100000
0<
#105000
b111111101101 1
b111111101101 T
b111111101101 c
b111111101101 q
b1000 (
b1000 a
b1000 v
b1000 {
b1100 0
b1100 S
b1100 X
b1100 r
b1100 C
b1100 \
b111 z
b111111101110 u
b1001 p
b1000 o
b111 !"
b111111101110 U
b11111111111111111111111111110111 '
b11111111111111111111111111110111 ]
b11111111111111111111111111110111 w
b11111111111111111111111111110111 |
b11111111111111111111111111110111 G
b11111111111111111111111111110111 _
1H
b101000 :
b101000 W
1;
b1100 )"
b1011 L
b11110100001000110101 P
1<
#110000
0<
#115000
b1111 &
b1111 `
b1111 y
b1111 ~
bx #
bx ^
bx x
bx }
b111111101100 1
b111111101100 T
b111111101100 c
b111111101100 q
b1001 (
b1001 a
b1001 v
b1001 {
b1101 0
b1101 S
b1101 X
b1101 r
b1101 C
b1101 \
b111111101101 U
b1000 !"
b1001 o
b1010 p
1%
1k
12
b111111101101 u
b1000 z
b1101 )"
b1100 L
b11110100001000110100 P
1<
#120000
0<
#125000
b0 &
b0 `
b0 y
b0 ~
b11111111111111111111111111110111 #
b11111111111111111111111111110111 ^
b11111111111111111111111111110111 x
b11111111111111111111111111110111 }
b111111101011 1
b111111101011 T
b111111101011 c
b111111101011 q
b1010 (
b1010 a
b1010 v
b1010 {
b1110 0
b1110 S
b1110 X
b1110 r
b1110 C
b1110 \
0H
0;
b1001 z
b111111101100 u
0%
0k
02
b1011 p
b1010 o
b1001 !"
b111111101100 U
b1110 )"
b1101 L
b10111 &"
b101100 %"
b11 N
b11110100001000110011 P
1<
#130000
0<
#135000
b0 1
b0 T
b0 c
b0 q
b0 (
b0 a
b0 v
b0 {
b1111 0
b1111 S
b1111 X
b1111 r
b1111 C
b1111 \
b111111101011 U
b1010 !"
b1011 o
b1100 p
b111111101011 u
b1010 z
b10111 '
b10111 ]
b10111 w
b10111 |
b10111 G
b10111 _
1H
b101100 :
b101100 W
1;
b1111 )"
b1110 L
b11110100001000110010 P
1<
#140000
0<
#145000
b1111 !
b1111 Q
b1111 Y
b1111 s
b1111 &
b1111 `
b1111 y
b1111 ~
b0 #
b0 ^
b0 x
b0 }
b0 ("
b0 '"
b0 N
b10000 0
b10000 S
b10000 X
b10000 r
b10000 C
b10000 \
b0 z
b0 u
1%
1k
12
b1101 p
b10 n
1+
1*
1l
b0 !"
b0 U
b10000 )"
b1111 L
b11110100001000110001 P
1<
#150000
0<
#155000
b0 &
b0 `
b0 y
b0 ~
b10000 !
b10000 Q
b10000 Y
b10000 s
b10111 #
b10111 ^
b10111 x
b10111 }
b10001 0
b10001 S
b10001 X
b10001 r
b10001 C
b10001 \
0H
0;
b0 n
b0 o
b0 ,
b0 [
b0 g
0+
0*
0l
b1110 p
0%
0k
02
b10001 )"
b10000 L
b11111111111111111111111111110110 &"
b100100 %"
b1 N
b11110100001000110000 P
1<
#160000
0<
#165000
b11 1
b11 T
b11 c
b11 q
b10001 !
b10001 Q
b10001 Y
b10001 s
b10010 0
b10010 S
b10010 X
b10010 r
b10010 C
b10010 \
b1111 p
b1 n
b11 m
b11111111111111111111111111110110 '
b11111111111111111111111111110110 ]
b11111111111111111111111111110110 w
b11111111111111111111111111110110 |
b11111111111111111111111111110110 G
b11111111111111111111111111110110 _
1H
b100100 :
b100100 W
1;
b10010 )"
b10001 L
b10 ("
b11111111111111111111111111100011 '"
b10 N
b11110100001000101111 P
1<
#170000
0<
#175000
b1111 &
b1111 `
b1111 y
b1111 ~
b10 1
b10 T
b10 c
b10 q
b1 (
b1 a
b1 v
b1 {
b10010 !
b10010 Q
b10010 Y
b10010 s
b10011 0
b10011 S
b10011 X
b10011 r
b10011 C
b10011 \
b11 U
b1 o
b110000111 ,
b110000111 [
b110000111 g
b10000 p
1%
1k
12
b11 u
b10011 )"
b10010 L
b11110100001000101110 P
1<
#180000
0<
#185000
b0 &
b0 `
b0 y
b0 ~
b1 1
b1 T
b1 c
b1 q
b10 (
b10 a
b10 v
b10 {
b11111111111111111111111111110110 #
b11111111111111111111111111110110 ^
b11111111111111111111111111110110 x
b11111111111111111111111111110110 }
b10011 !
b10011 Q
b10011 Y
b10011 s
b10100 0
b10100 S
b10100 X
b10100 r
b10100 C
b10100 \
0H
0;
b1 z
b10 u
0%
0k
02
b10001 p
b10 o
b1100100101 ,
b1100100101 [
b1100100101 g
b1 !"
b10 U
b10100 )"
b10011 L
b10111 &"
b101100 %"
b11 N
b11110100001000101101 P
1<
#190000
0<
#195000
b0 1
b0 T
b0 c
b0 q
b11 (
b11 a
b11 v
b11 {
b10100 !
b10100 Q
b10100 Y
b10100 s
b10101 0
b10101 S
b10101 X
b10101 r
b10101 C
b10101 \
b1 U
b10 !"
b11 o
b1001100111 ,
b1001100111 [
b1001100111 g
b10010 p
b1 u
b10 z
b10111 '
b10111 ]
b10111 w
b10111 |
b10111 G
b10111 _
1H
b101100 :
b101100 W
1;
b10101 )"
b10100 L
b11110100001000101100 P
1<
#200000
0<
#205000
b1111 &
b1111 `
b1111 y
b1111 ~
b111111111111 1
b111111111111 T
b111111111111 c
b111111111111 q
b100 (
b100 a
b100 v
b100 {
b10101 !
b10101 Q
b10101 Y
b10101 s
b10110 0
b10110 S
b10110 X
b10110 r
b10110 C
b10110 \
b11 z
b0 u
1%
1k
12
b10011 p
b100 o
b110011111 ,
b110011111 [
b110011111 g
b11 !"
b0 U
b10110 )"
b10101 L
b11110100001000101011 P
1<
#210000
0<
